LICENSE.txt
MANIFEST.in
README.md
setup.cfg
setup.py
topsis/__init__.py
topsis/topsis.py
topsis_harsh_102003694.egg-info/PKG-INFO
topsis_harsh_102003694.egg-info/SOURCES.txt
topsis_harsh_102003694.egg-info/dependency_links.txt
topsis_harsh_102003694.egg-info/top_level.txt