Metadata-Version: 2.1
Name: topsis-harsh-102003694
Version: 1.0.0
Summary: topsis implementation
Author: Harsh Bisla
Author-email: harshbisla10102001@gmail.com
Classifier: Programming Language :: Python :: 3
Classifier: License :: OSI Approved :: MIT License
Classifier: Operating System :: OS Independent
Requires-Python: >=3.6
License-File: LICENSE.txt
